pycvcam/__init__.py
pycvcam/__main__.py
pycvcam/__version__.py
pycvcam/compute_rays.py
pycvcam/distort_image.py
pycvcam/project_points.py
pycvcam/read_transform.py
pycvcam/undistort_image.py
pycvcam/undistort_points.py
pycvcam/write_transform.py
pycvcam/core/__init__.py
pycvcam/core/distortion.py
pycvcam/core/extrinsic.py
pycvcam/core/intrinsic.py
pycvcam/core/package.py
pycvcam/core/rays.py
pycvcam/core/transform.py
pycvcam/core/transform_result.py
pycvcam/distortion_objects/__init__.py
pycvcam/distortion_objects/cv2_distortion.py
pycvcam/distortion_objects/fisheye_distortion.py
pycvcam/distortion_objects/no_distortion.py
pycvcam/distortion_objects/zernike_distortion.py
pycvcam/extrinsic_objects/__init__.py
pycvcam/extrinsic_objects/cv2_extrinsic.py
pycvcam/extrinsic_objects/no_extrinsic.py
pycvcam/extrinsic_objects/orthographic_extrinsic.py
pycvcam/intrinsic_objects/__init__.py
pycvcam/intrinsic_objects/cv2_intrinsic.py
pycvcam/intrinsic_objects/no_intrinsic.py
pycvcam/intrinsic_objects/skew_intrinsic.py
pycvcam/optimize/__init__.py
pycvcam/optimize/optimize_input_points.py
pycvcam/optimize/optimize_parameters.py
pycvcam/resources/__init__.py
pycvcam/resources/definition.png
pycvcam/resources/definition.rst
pycvcam-1.5.3.dist-info/licenses/LICENSE
pycvcam-1.5.3.dist-info/METADATA
pycvcam-1.5.3.dist-info/WHEEL
pycvcam-1.5.3.dist-info/top_level.txt
pycvcam-1.5.3.dist-info/RECORD
