Metadata-Version: 2.4
Name: pycvcam
Version: 1.5.3
Summary: Python Computer Vision Cameras Operations and Models
Author-email: Artezaru <artezaru.github@proton.me>
License: Copyright 2025 Artezaru
Project-URL: Homepage, https://github.com/Artezaru/pycvcam
Project-URL: Documentation, https://Artezaru.github.io/pycvcam
Project-URL: Source, https://github.com/Artezaru/pycvcam
Project-URL: Tracker, https://github.com/Artezaru/pycvcam/issues
Classifier: Programming Language :: Python :: 3
Classifier: License :: OSI Approved :: Apache Software License
Classifier: Operating System :: OS Independent
Requires-Python: >=3.10
License-File: LICENSE
Requires-Dist: numpy>=1.26
Requires-Dist: opencv-python-headless>=4.9
Requires-Dist: scipy>=1.12
Requires-Dist: pyzernike-polynomials>=2.0.5
Requires-Dist: py3dframe>=1.0.1
Provides-Extra: dev
Requires-Dist: sphinx; extra == "dev"
Requires-Dist: pydata-sphinx-theme; extra == "dev"
Requires-Dist: numpydoc; extra == "dev"
Requires-Dist: pytest; extra == "dev"
Requires-Dist: pytest-cov; extra == "dev"
Requires-Dist: bumpver; extra == "dev"
Requires-Dist: twine; extra == "dev"
Requires-Dist: wheel; extra == "dev"
Requires-Dist: build; extra == "dev"
Requires-Dist: setuptools; extra == "dev"
Requires-Dist: setuptools-scm; extra == "dev"
Dynamic: license-file
